predictmarket/__init__.py
predictmarket/client.py
predictmarket/exceptions.py
predictmarket-0.2.1.dist-info/licenses/LICENSE
predictmarket-0.2.1.dist-info/METADATA
predictmarket-0.2.1.dist-info/WHEEL
predictmarket-0.2.1.dist-info/top_level.txt
predictmarket-0.2.1.dist-info/RECORD
