Metadata-Version: 2.4
Name: predictmarket
Version: 0.2.1
Summary: Python client for the Prediction Markets API
Author-email: Prediction Markets <info@predictmarket.ai>
License: MIT
Project-URL: Homepage, https://predictmarket.ai
Project-URL: Documentation, https://github.com/predict-market/api-python
Project-URL: Repository, https://github.com/predict-market/api-python
Project-URL: Bug Tracker, https://github.com/predict-market/api-python/issues
Keywords: prediction,markets,api,client,kalshi,polymarket
Classifier: Development Status :: 4 - Beta
Classifier: Intended Audience :: Developers
Classifier: Programming Language :: Python :: 3
Classifier: Programming Language :: Python :: 3.8
Classifier: Programming Language :: Python :: 3.9
Classifier: Programming Language :: Python :: 3.10
Classifier: Programming Language :: Python :: 3.11
Classifier: Programming Language :: Python :: 3.12
Classifier: Programming Language :: Python :: 3.13
Classifier: Programming Language :: Python :: 3.14
Requires-Python: >=3.8
License-File: LICENSE
Requires-Dist: httpx>=0.27.0
Provides-Extra: dev
Requires-Dist: pytest>=7.0.0; extra == "dev"
Requires-Dist: pytest-cov>=4.0.0; extra == "dev"
Requires-Dist: black>=23.0.0; extra == "dev"
Requires-Dist: mypy>=1.0.0; extra == "dev"
Dynamic: license-file
